lru/CacheStorage.py
lru/LRUCache.py
lru/LRULinkedList.py
lru/MemoryStorage.py
lru/ShelvedStorage.py
lru/Sqlite3Storage.py
lru/__init__.py
lru/utils.py
python_lru-0.2.1.dist-info/LICENSE
python_lru-0.2.1.dist-info/METADATA
python_lru-0.2.1.dist-info/WHEEL
python_lru-0.2.1.dist-info/top_level.txt
python_lru-0.2.1.dist-info/RECORD
