Metadata-Version: 2.1
Name: python-lru
Version: 0.2.1
Summary: LRU Cache Implementation
Home-page: https://github.com/shearern/lru
Author: Nathan Shearer
Author-email: shearern@gmail.com
License: UNKNOWN
Platform: UNKNOWN
Classifier: Programming Language :: Python :: 3
Classifier: Operating System :: OS Independent
Requires-Python: >=3.6
